{
  "year": 2007,
  "paperType": "English I",
  "paper": "英语一",
  "section": "Reading Comprehension",
  "textNumber": "Text 3",
  "title": "",
  "status": "已有数据",
  "passage": "During the past generation, the American middle-class family that once\ncould count on hard work and fair play to keep itself financially secure\nhas been transformed by economic risk and new realities. Now a pink slip,\na bad diagnosis, or a disappearing spouse can reduce a family from\nsolidly middle class to newly poor in a few months.\n\nIn just one generation, millions of mothers have gone to\nwork, transforming basic family economics. Scholars, policymakers, and\ncritics of all stripes have debated the social implications of these\nchanges, but few have looked at the side effect: family risk has risen\nas well. Today's families have budgeted to the limits of theirs new\ntwo-paycheck status. As a result, they have lost the parachute they once\nhad in times of financial setback - a back-up earner (usually Mom) who\ncould go into the workforce if the primary earner got laid off or fell\nsick. This \"added-worker effect\" could support the safety net offered\nby unemployment insurance or disability insurance to help families\nweather bad times. But today, a disruption to family fortunes can no\nlonger be made up with extra income from an otherwise-stay-at-home\npartner.\n\nDuring the same period, families have been asked to absorb much more\nrisk in their retirement income. Steelworkers, airline employees, and\nnow those in the auto industry are joining millions of families who must\nworry about interest rates, stock market fluctuation, and the harsh\nreality that they may outlive their retirement money. For much of the\npast year, President Bush campaigned to move Social Security to a\nsavings-account model, with retirees trading much or all of their\nguaranteed payments for payments depending on investment returns. For\nyounger families, the picture is not any better. Both the absolute cost\nof healthcare and the share of it borne by families have risen - and\nnewly fashionable health-savings plans are spreading from legislative\nhalls to Wal-Mart workers, with much higher deductibles and a large new\ndose of investment risk for families' future healthcare. Even\ndemographics are working against the middle class family, as the odds of\nhaving a weak elderly parent - and all the attendant need for physical\nand financial assistance - have jumped eightfold in just one generation.\n\nFrom the middle-class family perspective, much of this, understandably,\nlooks far less like an opportunity to exercise more financial\nresponsibility, and a good deal more like a frightening acceleration of\nthe wholesale shift of financial risk onto their already overburdened\nshoulders. The financial fallout has begun, and the political fallout\nmay not be far behind.",
  "questions": [
    {
      "id": "2007-text3-q31",
      "questionNumber": 31,
      "questionText": "Today's double-income families are at greater financial risk in that ____.",
      "question": "Today's double-income families are at greater financial risk in that ____.",
      "options": {
        "A": "the safety net they used to enjoy has disappeared",
        "B": "their chances of being laid off have greatly increased",
        "C": "they are more vulnerable to changes in family economics",
        "D": "they are deprived of unemployment or disability insurance"
      },
      "answer": "C",
      "type": "细节题",
      "questionType": "细节题",
      "explanation": "本题考查细节题。结合解析资料和原文P2，正确项为 C：they are more vulnerable to changes in family economics。其他选项主要与原文范围、逻辑或表达重点不符。",
      "trapAnalysis": "干扰项常见方式是偷换概念、扩大缩小范围或忽略同义替换。",
      "commonMistake": "容易定位不准或没有识别原文和选项的同义替换。",
      "location": "P2",
      "thinkingMethod": "先根据题干判断题型（细节题），再回原文定位，最后检查选项是否存在范围、态度或逻辑偷换。",
      "examinerThinking": {
        "sourceSentence": "P2",
        "testPoint": "细节题",
        "trap": "干扰项常见方式是偷换概念、扩大缩小范围或忽略同义替换。",
        "correctLogic": "本题考查细节题。结合解析资料和原文P2，正确项为 C：they are more vulnerable to changes in family economics。其他选项主要与原文范围、逻辑或表达重点不符。",
        "wrongOptionAnalysis": {
          "A": "待补充",
          "B": "待补充",
          "C": "待补充",
          "D": "待补充"
        },
        "nextTimeStrategy": "先根据题干判断题型（细节题），再回原文定位，最后检查选项是否存在范围、态度或逻辑偷换。"
      },
      "sourceSentenceAnalysis": null
    },
    {
      "id": "2007-text3-q32",
      "questionNumber": 32,
      "questionText": "As a result of President Bush's reform, retired people may have ____.",
      "question": "As a result of President Bush's reform, retired people may have ____.",
      "options": {
        "A": "a higher sense of security",
        "B": "less secured payments",
        "C": "less chance to invest",
        "D": "a guaranteed future"
      },
      "answer": "B",
      "type": "细节题",
      "questionType": "细节题",
      "explanation": "本题考查细节题。结合解析资料和原文P3，正确项为 B：less secured payments。其他选项主要与原文范围、逻辑或表达重点不符。",
      "trapAnalysis": "干扰项常见方式是偷换概念、扩大缩小范围或忽略同义替换。",
      "commonMistake": "容易定位不准或没有识别原文和选项的同义替换。",
      "location": "P3",
      "thinkingMethod": "先根据题干判断题型（细节题），再回原文定位，最后检查选项是否存在范围、态度或逻辑偷换。",
      "examinerThinking": {
        "sourceSentence": "P3",
        "testPoint": "细节题",
        "trap": "干扰项常见方式是偷换概念、扩大缩小范围或忽略同义替换。",
        "correctLogic": "本题考查细节题。结合解析资料和原文P3，正确项为 B：less secured payments。其他选项主要与原文范围、逻辑或表达重点不符。",
        "wrongOptionAnalysis": {
          "A": "待补充",
          "B": "待补充",
          "C": "待补充",
          "D": "待补充"
        },
        "nextTimeStrategy": "先根据题干判断题型（细节题），再回原文定位，最后检查选项是否存在范围、态度或逻辑偷换。"
      },
      "sourceSentenceAnalysis": null
    },
    {
      "id": "2007-text3-q33",
      "questionNumber": 33,
      "questionText": "According to the author, health-savings plans will ____.",
      "question": "According to the author, health-savings plans will ____.",
      "options": {
        "A": "help reduce the cost of healthcare",
        "B": "popularize among the middle class",
        "C": "compensate for the reduced pensions",
        "D": "increase the families' investment risk"
      },
      "answer": "D",
      "type": "细节题",
      "questionType": "细节题",
      "explanation": "本题考查细节题。结合解析资料和原文P3，正确项为 D：increase the families' investment risk。其他选项主要与原文范围、逻辑或表达重点不符。",
      "trapAnalysis": "干扰项常见方式是偷换概念、扩大缩小范围或忽略同义替换。",
      "commonMistake": "容易定位不准或没有识别原文和选项的同义替换。",
      "location": "P3",
      "thinkingMethod": "先根据题干判断题型（细节题），再回原文定位，最后检查选项是否存在范围、态度或逻辑偷换。",
      "examinerThinking": {
        "sourceSentence": "P3",
        "testPoint": "细节题",
        "trap": "干扰项常见方式是偷换概念、扩大缩小范围或忽略同义替换。",
        "correctLogic": "本题考查细节题。结合解析资料和原文P3，正确项为 D：increase the families' investment risk。其他选项主要与原文范围、逻辑或表达重点不符。",
        "wrongOptionAnalysis": {
          "A": "待补充",
          "B": "待补充",
          "C": "待补充",
          "D": "待补充"
        },
        "nextTimeStrategy": "先根据题干判断题型（细节题），再回原文定位，最后检查选项是否存在范围、态度或逻辑偷换。"
      },
      "sourceSentenceAnalysis": null
    },
    {
      "id": "2007-text3-q34",
      "questionNumber": 34,
      "questionText": "It can be inferred from the last paragraph that ____.",
      "question": "It can be inferred from the last paragraph that ____.",
      "options": {
        "A": "financial risks tend to outweigh political risks",
        "B": "the middle class may face greater political challenges",
        "C": "financial problems may bring about political problems",
        "D": "financial responsibility is an indicator of political status"
      },
      "answer": "C",
      "type": "推理题",
      "questionType": "推理题",
      "explanation": "本题考查推理题。结合解析资料和原文P最后一段，正确项为 C：financial problems may bring about political problems。其他选项主要与原文范围、逻辑或表达重点不符。",
      "trapAnalysis": "干扰项常过度推理或把可能性改写成确定结论。",
      "commonMistake": "容易过度推理，没有把结论限定在原文可支持范围内。",
      "location": "P最后一段",
      "thinkingMethod": "先根据题干判断题型（推理题），再回原文定位，最后检查选项是否存在范围、态度或逻辑偷换。",
      "examinerThinking": {
        "sourceSentence": "P最后一段",
        "testPoint": "推理题",
        "trap": "干扰项常过度推理或把可能性改写成确定结论。",
        "correctLogic": "本题考查推理题。结合解析资料和原文P最后一段，正确项为 C：financial problems may bring about political problems。其他选项主要与原文范围、逻辑或表达重点不符。",
        "wrongOptionAnalysis": {
          "A": "待补充",
          "B": "待补充",
          "C": "待补充",
          "D": "待补充"
        },
        "nextTimeStrategy": "先根据题干判断题型（推理题），再回原文定位，最后检查选项是否存在范围、态度或逻辑偷换。"
      },
      "sourceSentenceAnalysis": null
    },
    {
      "id": "2007-text3-q35",
      "questionNumber": 35,
      "questionText": "Which of the following is the best title for this text?",
      "question": "Which of the following is the best title for this text?",
      "options": {
        "A": "The Middle Class on the Alert",
        "B": "The Middle Class on the Cliff",
        "C": "The Middle Class in Conflict",
        "D": "The Middle Class in Ruins ---"
      },
      "answer": "B",
      "type": "主旨题",
      "questionType": "主旨题",
      "explanation": "本题考查主旨题。结合解析资料和原文TODO: 定位句待人工核对，正确项为 B：The Middle Class on the Cliff。其他选项主要与原文范围、逻辑或表达重点不符。",
      "trapAnalysis": "干扰项常抓局部细节，但不能概括全文或段落中心。",
      "commonMistake": "容易把举例或局部信息当成全文中心。",
      "location": "TODO: 定位句待人工核对",
      "thinkingMethod": "先根据题干判断题型（主旨题），再回原文定位，最后检查选项是否存在范围、态度或逻辑偷换。",
      "examinerThinking": {
        "sourceSentence": "TODO: 定位句待人工核对",
        "testPoint": "主旨题",
        "trap": "干扰项常抓局部细节，但不能概括全文或段落中心。",
        "correctLogic": "本题考查主旨题。结合解析资料和原文TODO: 定位句待人工核对，正确项为 B：The Middle Class on the Cliff。其他选项主要与原文范围、逻辑或表达重点不符。",
        "wrongOptionAnalysis": {
          "A": "待补充",
          "B": "待补充",
          "C": "待补充",
          "D": "待补充"
        },
        "nextTimeStrategy": "先根据题干判断题型（主旨题），再回原文定位，最后检查选项是否存在范围、态度或逻辑偷换。"
      },
      "sourceSentenceAnalysis": null
    }
  ],
  "vocabulary": [],
  "vocabularyGroups": {
    "coreWords": [
      {
        "word": "middle-class",
        "meaning": "adj.中层社会的，中产阶级的",
        "sentence": "待补充",
        "sourceParagraph": 0,
        "note": "解析已按资料整理为短版训练解析；未能可靠定位的内容保留TODO。"
      },
      {
        "word": "counton",
        "meaning": "依靠，指望",
        "sentence": "待补充",
        "sourceParagraph": 0,
        "note": "解析已按资料整理为短版训练解析；未能可靠定位的内容保留TODO。"
      },
      {
        "word": "fairplay",
        "meaning": "按规则比赛；公平办事",
        "sentence": "待补充",
        "sourceParagraph": 0,
        "note": "解析已按资料整理为短版训练解析；未能可靠定位的内容保留TODO。"
      },
      {
        "word": "pinkslip",
        "meaning": "解雇通知书",
        "sentence": "待补充",
        "sourceParagraph": 0,
        "note": "解析已按资料整理为短版训练解析；未能可靠定位的内容保留TODO。"
      },
      {
        "word": "spouse",
        "meaning": "n.配偶(指夫或妻",
        "sentence": "待补充",
        "sourceParagraph": 0,
        "note": "解析已按资料整理为短版训练解析；未能可靠定位的内容保留TODO。"
      },
      {
        "word": "debate",
        "meaning": "v./n.争论，辩论",
        "sentence": "待补充",
        "sourceParagraph": 0,
        "note": "解析已按资料整理为短版训练解析；未能可靠定位的内容保留TODO。"
      },
      {
        "word": "implication",
        "meaning": "n.牵连，含义，暗示",
        "sentence": "待补充",
        "sourceParagraph": 0,
        "note": "解析已按资料整理为短版训练解析；未能可靠定位的内容保留TODO。"
      },
      {
        "word": "parachute",
        "meaning": "n.降落伞",
        "sentence": "待补充",
        "sourceParagraph": 0,
        "note": "解析已按资料整理为短版训练解析；未能可靠定位的内容保留TODO。"
      },
      {
        "word": "disruption",
        "meaning": "n.中断，瓦解，破坏",
        "sentence": "待补充",
        "sourceParagraph": 0,
        "note": "解析已按资料整理为短版训练解析；未能可靠定位的内容保留TODO。"
      },
      {
        "word": "absorb",
        "meaning": "vt.吸收，吸引",
        "sentence": "待补充",
        "sourceParagraph": 0,
        "note": "解析已按资料整理为短版训练解析；未能可靠定位的内容保留TODO。"
      }
    ],
    "familiarWordsWithNewMeanings": []
  },
  "longSentences": [],
  "articleStructure": "待补充",
  "notes": "解析已按资料整理为短版训练解析；未能可靠定位的内容保留TODO。",
  "sources": [
    {
      "name": "公开答案详解PDF",
      "url": "https://raw.githubusercontent.com/swjtuhub/SWJTU-Courses/main/%E8%80%83%E7%A0%94%E8%B5%84%E6%96%99/%E8%8B%B1%E8%AF%AD/%E7%9C%9F%E9%A2%98/%E8%8B%B1%E8%AF%AD%E4%B8%80%E7%AD%94%E6%A1%88%E8%A7%A3%E6%9E%90/2007%E5%B9%B4%E8%80%83%E7%A0%94%E8%8B%B1%E8%AF%AD%E7%9C%9F%E9%A2%98%E7%AD%94%E6%A1%88%E5%8F%8A%E8%A7%A3%E6%9E%90.pdf"
    }
  ]
}
